<?xml version='1.0' encoding='utf-8' ?>
<XML>
	<Object Id="DescID_Building000" Chinese="营地·一级" English="" French="" Spanish="" />
	<Object Id="DescID_Building001" Chinese="营地·二级" English="" French="" Spanish="" />
	<Object Id="DescID_Building002" Chinese="营地·三级" English="" French="" Spanish="" />
	<Object Id="DescID_Building010" Chinese="炸弹·一级" English="" French="" Spanish="" />
	<Object Id="DescID_Building011" Chinese="炸弹·二级" English="" French="" Spanish="" />
	<Object Id="DescID_Building012" Chinese="炸弹·三级" English="" French="" Spanish="" />
	<Object Id="DescID_Building020" Chinese="减甲炮·一级" English="" French="" Spanish="" />
	<Object Id="DescID_Building021" Chinese="减甲炮·二级" English="" French="" Spanish="" />
	<Object Id="DescID_Building022" Chinese="减甲炮·三级" English="" French="" Spanish="" />
	<Object Id="DescID_Building030" Chinese="加农炮·一级" English="" French="" Spanish="" />
	<Object Id="DescID_Building031" Chinese="加农炮·二级" English="" French="" Spanish="" />
	<Object Id="DescID_Building032" Chinese="加农炮·三级" English="" French="" Spanish="" />
	<Object Id="DescID_Building040" Chinese="冰塔·一级" English="" French="" Spanish="" />
	<Object Id="DescID_Building041" Chinese="冰塔·二级" English="" French="" Spanish="" />
	<Object Id="DescID_Building042" Chinese="冰塔·三级" English="" French="" Spanish="" />
	<Object Id="DescID_Building050" Chinese="能源产生器·一级" English="" French="" Spanish="" />
	<Object Id="DescID_Building051" Chinese="能源产生器·二级" English="" French="" Spanish="" />
	<Object Id="DescID_Building052" Chinese="能源产生器·三级" English="" French="" Spanish="" />
	<Object Id="DescID_Building060" Chinese="能源存储器·一级" English="" French="" Spanish="" />
	<Object Id="DescID_Building061" Chinese="能源存储器·二级" English="" French="" Spanish="" />
	<Object Id="DescID_Building062" Chinese="能源存储器·三级" English="" French="" Spanish="" />
	<Object Id="DescID_Building070" Chinese="火焰发射器·一级" English="" French="" Spanish="" />
	<Object Id="DescID_Building071" Chinese="火焰发射器·二级" English="" French="" Spanish="" />
	<Object Id="DescID_Building072" Chinese="火焰发射器·三级" English="" French="" Spanish="" />
	<Object Id="DescID_Building080" Chinese="加特林机枪·一级" English="" French="" Spanish="" />
	<Object Id="DescID_Building081" Chinese="加特林机枪·二级" English="" French="" Spanish="" />
	<Object Id="DescID_Building082" Chinese="加特林机枪·三级" English="" French="" Spanish="" />
	<Object Id="DescID_Building090" Chinese="高斯电磁炮·一级" English="" French="" Spanish="" />
	<Object Id="DescID_Building091" Chinese="高斯电磁炮·二级" English="" French="" Spanish="" />
	<Object Id="DescID_Building092" Chinese="高斯电磁炮·三级" English="" French="" Spanish="" />
	<Object Id="DescID_Building100" Chinese="金矿·一级" English="" French="" Spanish="" />
	<Object Id="DescID_Building101" Chinese="金矿·二级" English="" French="" Spanish="" />
	<Object Id="DescID_Building102" Chinese="金矿·三级" English="" French="" Spanish="" />
	<Object Id="DescID_Building110" Chinese="金罐·一级" English="" French="" Spanish="" />
	<Object Id="DescID_Building111" Chinese="金罐·二级" English="" French="" Spanish="" />
	<Object Id="DescID_Building112" Chinese="金罐·三级" English="" French="" Spanish="" />
	<Object Id="DescID_Building120" Chinese="重锤·一级" English="" French="" Spanish="" />
	<Object Id="DescID_Building121" Chinese="重锤·二级" English="" French="" Spanish="" />
	<Object Id="DescID_Building122" Chinese="重锤·三级" English="" French="" Spanish="" />
	<Object Id="DescID_Building130" Chinese="镭射激光器·一级" English="" French="" Spanish="" />
	<Object Id="DescID_Building131" Chinese="镭射激光器·二级" English="" French="" Spanish="" />
	<Object Id="DescID_Building132" Chinese="镭射激光器·三级" English="" French="" Spanish="" />
	<Object Id="DescID_Building140" Chinese="麦肯锡机枪·一级" English="" French="" Spanish="" />
	<Object Id="DescID_Building141" Chinese="麦肯锡机枪·二级" English="" French="" Spanish="" />
	<Object Id="DescID_Building142" Chinese="麦肯锡机枪·三级" English="" French="" Spanish="" />
	<Object Id="DescID_Building150" Chinese="迫击炮·一级" English="" French="" Spanish="" />
	<Object Id="DescID_Building151" Chinese="迫击炮·二级" English="" French="" Spanish="" />
	<Object Id="DescID_Building152" Chinese="迫击炮·三级" English="" French="" Spanish="" />
	<Object Id="DescID_Building160" Chinese="等离子炮·一级" English="" French="" Spanish="" />
	<Object Id="DescID_Building161" Chinese="等离子炮·二级" English="" French="" Spanish="" />
	<Object Id="DescID_Building162" Chinese="等离子炮·三级" English="" French="" Spanish="" />
	<Object Id="DescID_Building170" Chinese="探照灯·一级 - 启动需要消耗能源 50点每小时，工会驻地的最佳防御武器，可探测6米内的隐形单位，如探测到敌对单位，将自动召唤6米内的火箭导弹进行攻击" English="" French="" Spanish="" />
	<Object Id="DescID_Building171" Chinese="探照灯·二级 - 启动需要消耗能源 100点每小时，工会驻地的最佳防御武器，可探测10米内的隐形单位，如探测到敌对单位，将自动召唤10米内直升机(如有)进行攻击" English="" French="" Spanish="" />
	<Object Id="DescID_Building172" Chinese="探照灯·三级 - 启动需要消耗能源 200点每小时，工会驻地的最佳防御武器，可探测15米内的隐形单位，如探测到敌对单位，将自动召唤15米内的战斗飞船(如有)进行攻击" English="" French="" Spanish="" />
	<Object Id="DescID_Building180" Chinese="雷达·一级 - 启动需要消耗能源 50点每小时，工会驻地的最佳防御武器，可探测6米内的隐形单位，如探测到敌对单位，将自动召唤6米内的火箭导弹进行攻击" English="" French="" Spanish="" />
	<Object Id="DescID_Building181" Chinese="雷达·二级 - 启动需要消耗能源 100点每小时，工会驻地的最佳防御武器，可探测10米内的隐形单位，如探测到敌对单位，将自动召唤10米内直升机(如有)进行攻击" English="" French="" Spanish="" />
	<Object Id="DescID_Building182" Chinese="雷达·三级 - 启动需要消耗能源 200点每小时，工会驻地的最佳防御武器，可探测15米内的隐形单位，如探测到敌对单位，将自动召唤15米内的战斗飞船(如有)进行攻击" English="" French="" Spanish="" />
	<Object Id="DescID_Building190" Chinese="火箭·一级" English="" French="" Spanish="" />
	<Object Id="DescID_Building191" Chinese="火箭·二级" English="" French="" Spanish="" />
	<Object Id="DescID_Building192" Chinese="火箭·三级" English="" French="" Spanish="" />
	<Object Id="DescID_Building200" Chinese="雷电发射器·一级" English="" French="" Spanish="" />
	<Object Id="DescID_Building201" Chinese="雷电发射器·二级" English="" French="" Spanish="" />
	<Object Id="DescID_Building202" Chinese="雷电发射器·三级" English="" French="" Spanish="" />
	<Object Id="DescID_Building210" Chinese="穿刺怒·一级" English="" French="" Spanish="" />
	<Object Id="DescID_Building211" Chinese="穿刺怒·二级" English="" French="" Spanish="" />
	<Object Id="DescID_Building212" Chinese="穿刺怒·三级" English="" French="" Spanish="" />
	<Object Id="DescID_Building220" Chinese="火龙炮·一级" English="" French="" Spanish="" />
	<Object Id="DescID_Building221" Chinese="火龙炮·二级" English="" French="" Spanish="" />
	<Object Id="DescID_Building222" Chinese="火龙炮·三级" English="" French="" Spanish="" />
	<Object Id="DescID_Hero001" Chinese="他就是个刺客，你希望他干啥？" English="Ogre mages use bat balls to fire their weapons and then chase them in frenzied killings. 
Although they lack wisdom, but they very luckly which often double or even three times hurt." French="" Spanish="" />
	<Object Id="DescID_Hero002" Chinese="唐僧话最多" English="A member of a mythical race of short, stocky human-like creatures who are generally skilled in mining and metalworking." French="" Spanish="" />
	<Object Id="DescID_Hero003" Chinese="日本的流浪忍者" English="The wererat is one of several different types of animalistic forms. They are classified as 'lycanthropes', despite the fact that the term reflects a lupine, or wolven" French="" Spanish="" />
	<Object Id="DescID_Hero004" Chinese="日本的流浪剑客" English="Yao Li was a famed assassin in the Spring and Autumn period." French="" Spanish="" />
	<Object Id="DescID_Hero005" Chinese="狂战士，就知道打架" English="" French="" Spanish="" />
	<Object Id="DescID_Hero006" Chinese="据说他当年发现了新大陆？" English="" French="" Spanish="" />
	<Object Id="DescID_Hero007" Chinese="矮人国王，好很有钱的样子？" English="" French="" Spanish="" />
	<Object Id="DescID_Hero008" Chinese="不知道怎么说，反正很厉害的样子。" English="" French="" Spanish="" />
	<Object Id="DescID_Hero009" Chinese="可不要被这个小姐姐的样子蒙蔽了。" English="" French="" Spanish="" />
	<Object Id="DescID_Hero010" Chinese="斯巴达克斯，不要得罪他，小心他300弟弟打你。" English="" French="" Spanish="" />
	<Object Id="DescID_Hero011" Chinese="烧死他们！" English="Burn them all!" French="" Spanish="" />
	<Object Id="DescID_Hero012" Chinese="嗯，烧死他们！" English="" French="" Spanish="" />
	<Object Id="DescID_Hero013" Chinese="射射射！" English="" French="" Spanish="" />
	<Object Id="DescID_Hero014" Chinese="我要召唤蛇！" English="" French="" Spanish="" />
	<Object Id="DescID_Hero015" Chinese="鼠子鼠孙无穷尽！" English="" French="" Spanish="" />
	<Object Id="DescID_Hero016" Chinese="据说挖矿很厉害？" English="" French="" Spanish="" />
	<Object Id="DescID_Hero017" Chinese="食人魔法师使用蝙蝠球火焰点燃他们的武器，然后追着他们在疯狂的杀戮。虽然他们缺少智慧，但是运气绝对好，经常打出双倍甚至三倍伤害。" English="" French="" Spanish="" />
	<Object Id="DescID_Hero018" Chinese="你这野猴！" English="" French="" Spanish="" />
	<Object Id="DescID_Hero019" Chinese="不认识" English="" French="" Spanish="" />
	<Object Id="DescID_NPC001" Chinese="食人魔法师使用蝙蝠球火焰点燃他们的武器，然后追着他们在疯狂的杀戮。虽然他们缺少智慧，但是运气绝对好，经常打出双倍甚至三倍伤害。" English="Ogre mages use bat balls to fire their weapons and then chase them in frenzied killings. 
Although they lack wisdom, but they very luckly which often double or even three times hurt." French="" Spanish="" />
	<Object Id="DescID_NPC002" Chinese="矮人热衷于挖矿、铸造、手工艺和收集金银财货." English="A member of a mythical race of short, stocky human-like creatures who are generally skilled in mining and metalworking." French="" Spanish="" />
	<Object Id="DescID_NPC003" Chinese="狼人是一个力量型近战英雄，拥有巨大的物理能力和可观的移动速度， 擅长推进建筑和增加队伍的攻击力和生命值" English="The wererat is one of several different types of animalistic forms. They are classified as 'lycanthropes', despite the fact that the term reflects a lupine, or wolven" French="" Spanish="" />
	<Object Id="DescID_NPC004" Chinese="要离是人族最悲情的刺客--神魔大战中，自断一臂假意投靠鬼族，然而再次断臂换来重伤夜王." English="Yao Li was a famed assassin in the Spring and Autumn period." French="" Spanish="" />
	<Object Id="DescID_NPC005" Chinese="" English="" French="" Spanish="" />
	<Object Id="DescID_NPC006" Chinese="" English="" French="" Spanish="" />
	<Object Id="DescID_NPC007" Chinese="" English="" French="" Spanish="" />
	<Object Id="DescID_NPC008" Chinese="" English="" French="" Spanish="" />
	<Object Id="DescID_NPC009" Chinese="" English="" French="" Spanish="" />
	<Object Id="DescID_NPC010" Chinese="" English="" French="" Spanish="" />
	<Object Id="DescID_NPC011" Chinese="" English="" French="" Spanish="" />
	<Object Id="DescID_NPC012" Chinese="" English="" French="" Spanish="" />
	<Object Id="DescID_NPC013" Chinese="" English="" French="" Spanish="" />
	<Object Id="DescID_NPC014" Chinese="" English="" French="" Spanish="" />
	<Object Id="DescID_NPC015" Chinese="" English="" French="" Spanish="" />
	<Object Id="DescID_NPC016" Chinese="" English="" French="" Spanish="" />
	<Object Id="DescID_NPC017" Chinese="" English="" French="" Spanish="" />
	<Object Id="DescID_NPC018" Chinese="" English="" French="" Spanish="" />
	<Object Id="DescID_NPC019" Chinese="" English="" French="" Spanish="" />
	<Object Id="DescID_Special1_Hero001" Chinese="技能1描述*英雄001" English="" French="" Spanish="" />
	<Object Id="DescID_Special1_Hero002" Chinese="技能1描述*英雄002" English="" French="" Spanish="" />
	<Object Id="DescID_Special1_Hero003" Chinese="技能1描述*英雄003" English="" French="" Spanish="" />
	<Object Id="DescID_Special1_Hero004" Chinese="技能1描述*英雄004" English="" French="" Spanish="" />
	<Object Id="DescID_Special1_Hero005" Chinese="技能1描述*英雄005" English="" French="" Spanish="" />
	<Object Id="DescID_Special1_Hero006" Chinese="技能1描述*英雄006" English="" French="" Spanish="" />
	<Object Id="DescID_Special1_Hero007" Chinese="技能1描述*英雄007" English="" French="" Spanish="" />
	<Object Id="DescID_Special1_Hero008" Chinese="技能1描述*英雄008" English="" French="" Spanish="" />
	<Object Id="DescID_Special1_Hero009" Chinese="技能1描述*英雄009" English="" French="" Spanish="" />
	<Object Id="DescID_Special1_Hero010" Chinese="技能1描述*英雄010" English="" French="" Spanish="" />
	<Object Id="DescID_Special1_Hero011" Chinese="技能1描述*英雄011" English="" French="" Spanish="" />
	<Object Id="DescID_Special1_Hero012" Chinese="技能1描述*英雄012" English="" French="" Spanish="" />
	<Object Id="DescID_Special1_Hero013" Chinese="技能1描述*英雄013" English="" French="" Spanish="" />
	<Object Id="DescID_Special1_Hero014" Chinese="技能1描述*英雄014" English="" French="" Spanish="" />
	<Object Id="DescID_Special1_Hero015" Chinese="技能1描述*英雄015" English="" French="" Spanish="" />
	<Object Id="DescID_Special1_Hero016" Chinese="技能1描述*英雄016" English="" French="" Spanish="" />
	<Object Id="DescID_Special1_Hero017" Chinese="技能1描述*英雄017" English="" French="" Spanish="" />
	<Object Id="DescID_Special1_Hero018" Chinese="技能1描述*英雄018" English="" French="" Spanish="" />
	<Object Id="DescID_Special1_Hero019" Chinese="技能1描述*英雄019" English="" French="" Spanish="" />
	<Object Id="DescID_Special2_Hero001" Chinese="技能2描述*英雄001" English="" French="" Spanish="" />
	<Object Id="DescID_Special2_Hero002" Chinese="技能2描述*英雄002" English="" French="" Spanish="" />
	<Object Id="DescID_Special2_Hero003" Chinese="技能2描述*英雄003" English="" French="" Spanish="" />
	<Object Id="DescID_Special2_Hero004" Chinese="技能2描述*英雄004" English="" French="" Spanish="" />
	<Object Id="DescID_Special2_Hero005" Chinese="技能2描述*英雄005" English="" French="" Spanish="" />
	<Object Id="DescID_Special2_Hero006" Chinese="技能2描述*英雄006" English="" French="" Spanish="" />
	<Object Id="DescID_Special2_Hero007" Chinese="技能2描述*英雄007" English="" French="" Spanish="" />
	<Object Id="DescID_Special2_Hero008" Chinese="技能2描述*英雄008" English="" French="" Spanish="" />
	<Object Id="DescID_Special2_Hero009" Chinese="技能2描述*英雄009" English="" French="" Spanish="" />
	<Object Id="DescID_Special2_Hero010" Chinese="技能2描述*英雄010" English="" French="" Spanish="" />
	<Object Id="DescID_Special2_Hero011" Chinese="技能2描述*英雄011" English="" French="" Spanish="" />
	<Object Id="DescID_Special2_Hero012" Chinese="技能2描述*英雄012" English="" French="" Spanish="" />
	<Object Id="DescID_Special2_Hero013" Chinese="技能2描述*英雄013" English="" French="" Spanish="" />
	<Object Id="DescID_Special2_Hero014" Chinese="技能2描述*英雄014" English="" French="" Spanish="" />
	<Object Id="DescID_Special2_Hero015" Chinese="技能2描述*英雄015" English="" French="" Spanish="" />
	<Object Id="DescID_Special2_Hero016" Chinese="技能2描述*英雄016" English="" French="" Spanish="" />
	<Object Id="DescID_Special2_Hero017" Chinese="技能2描述*英雄017" English="" French="" Spanish="" />
	<Object Id="DescID_Special2_Hero018" Chinese="技能2描述*英雄018" English="" French="" Spanish="" />
	<Object Id="DescID_Special2_Hero019" Chinese="技能2描述*英雄019" English="" French="" Spanish="" />
	<Object Id="DescID_THUMP_Hero001" Chinese="觉醒技能描述*英雄001" English="" French="" Spanish="" />
	<Object Id="DescID_THUMP_Hero002" Chinese="觉醒技能描述*英雄002" English="" French="" Spanish="" />
	<Object Id="DescID_THUMP_Hero003" Chinese="觉醒技能描述*英雄003" English="" French="" Spanish="" />
	<Object Id="DescID_THUMP_Hero004" Chinese="觉醒技能描述*英雄004" English="" French="" Spanish="" />
	<Object Id="DescID_THUMP_Hero005" Chinese="觉醒技能描述*英雄005" English="" French="" Spanish="" />
	<Object Id="DescID_THUMP_Hero006" Chinese="觉醒技能描述*英雄006" English="" French="" Spanish="" />
	<Object Id="DescID_THUMP_Hero007" Chinese="觉醒技能描述*英雄007" English="" French="" Spanish="" />
	<Object Id="DescID_THUMP_Hero008" Chinese="觉醒技能描述*英雄008" English="" French="" Spanish="" />
	<Object Id="DescID_THUMP_Hero009" Chinese="觉醒技能描述*英雄009" English="" French="" Spanish="" />
	<Object Id="DescID_THUMP_Hero010" Chinese="觉醒技能描述*英雄010" English="" French="" Spanish="" />
	<Object Id="DescID_THUMP_Hero011" Chinese="觉醒技能描述*英雄011" English="" French="" Spanish="" />
	<Object Id="DescID_THUMP_Hero012" Chinese="觉醒技能描述*英雄012" English="" French="" Spanish="" />
	<Object Id="DescID_THUMP_Hero013" Chinese="觉醒技能描述*英雄013" English="" French="" Spanish="" />
	<Object Id="DescID_THUMP_Hero014" Chinese="觉醒技能描述*英雄014" English="" French="" Spanish="" />
	<Object Id="DescID_THUMP_Hero015" Chinese="觉醒技能描述*英雄015" English="" French="" Spanish="" />
	<Object Id="DescID_THUMP_Hero016" Chinese="觉醒技能描述*英雄016" English="" French="" Spanish="" />
	<Object Id="DescID_THUMP_Hero017" Chinese="觉醒技能描述*英雄017" English="" French="" Spanish="" />
	<Object Id="DescID_THUMP_Hero018" Chinese="觉醒技能描述*英雄018" English="" French="" Spanish="" />
	<Object Id="DescID_THUMP_Hero019" Chinese="觉醒技能描述*英雄019" English="" French="" Spanish="" />
	<Object Id="Desc_ATK_Water" Chinese="攻击药水，在一定时间内攻击翻倍！" English="" French="" Spanish="" />
	<Object Id="Desc_Avoid_Def_Water" Chinese="在一定时间内，无视对方防御！" English="" French="" Spanish="" />
	<Object Id="Desc_Card_Hero001" Chinese="英雄卷轴使用后可获得英雄 食人兽 /n 食人兽 介绍。。。" English="" French="" Spanish="" />
	<Object Id="Desc_Card_Hero002" Chinese="英雄卷轴使用后可获得英雄 矮人 /n 食人兽 介绍。。。" English="" French="" Spanish="" />
	<Object Id="Desc_Card_Hero003" Chinese="英雄卷轴使用后可获得英雄 鼠人 /n 食人兽 介绍。。。" English="" French="" Spanish="" />
	<Object Id="Desc_Card_Hero004" Chinese="英雄卷轴使用后可获得英雄  溪涧武士 /n 食人兽 介绍。。。" English="" French="" Spanish="" />
	<Object Id="Desc_Card_Hero005" Chinese="" English="" French="" Spanish="" />
	<Object Id="Desc_Card_Hero006" Chinese="" English="" French="" Spanish="" />
	<Object Id="Desc_Card_Hero007" Chinese="" English="" French="" Spanish="" />
	<Object Id="Desc_Card_Hero008" Chinese="" English="" French="" Spanish="" />
	<Object Id="Desc_Card_Hero009" Chinese="" English="" French="" Spanish="" />
	<Object Id="Desc_Card_Hero010" Chinese="" English="" French="" Spanish="" />
	<Object Id="Desc_Card_Hero011" Chinese="" English="" French="" Spanish="" />
	<Object Id="Desc_Card_Hero012" Chinese="" English="" French="" Spanish="" />
	<Object Id="Desc_Card_Hero013" Chinese="" English="" French="" Spanish="" />
	<Object Id="Desc_Card_Hero014" Chinese="" English="" French="" Spanish="" />
	<Object Id="Desc_Card_Hero015" Chinese="" English="" French="" Spanish="" />
	<Object Id="Desc_Card_Hero016" Chinese="" English="" French="" Spanish="" />
	<Object Id="Desc_Card_Hero017" Chinese="" English="" French="" Spanish="" />
	<Object Id="Desc_Card_Hero018" Chinese="" English="" French="" Spanish="" />
	<Object Id="Desc_Card_Hero019" Chinese="" English="" French="" Spanish="" />
	<Object Id="Desc_Damage_MP_Water" Chinese="进入范围内的英雄，自动丢蓝！" English="" French="" Spanish="" />
	<Object Id="Desc_Diamond_Item1" Chinese="一包钻石，使用后获得钻石。" English="" French="" Spanish="" />
	<Object Id="Desc_GEM_ATK" Chinese="攻击宝石！" English="" French="" Spanish="" />
	<Object Id="Desc_GEM_DEF" Chinese="防御宝石！" English="" French="" Spanish="" />
	<Object Id="Desc_GEM_FIRE" Chinese="火属性宝石！" English="" French="" Spanish="" />
	<Object Id="Desc_GEM_ICE" Chinese="冰属性宝石！" English="" French="" Spanish="" />
	<Object Id="Desc_GEM_LIGHT" Chinese="雷属性宝石！" English="" French="" Spanish="" />
	<Object Id="Desc_GEM_POISON" Chinese="毒属性宝石！" English="" French="" Spanish="" />
	<Object Id="Desc_GEM_WIND" Chinese="风属性宝石！" English="" French="" Spanish="" />
	<Object Id="Desc_Gold_Item1" Chinese="一包金币，使用后获得金币。" English="" French="" Spanish="" />
	<Object Id="Desc_HOLY_WATER" Chinese="小瓶圣水，在一定时间内防御翻倍！" English="" French="" Spanish="" />
	<Object Id="Desc_HP" Chinese="小瓶生命药水，增加英雄生命力！" English="" French="" Spanish="" />
	<Object Id="Desc_MP" Chinese="小瓶魔法药水，增加英雄魔法力！" English="" French="" Spanish="" />
	<Object Id="Desc_NoobPack" Chinese="新手升级礼包！" English="" French="" Spanish="" />
	<Object Id="Desc_Task1" Chinese="打开背包，获取一个英雄" English="" French="" Spanish="" />
	<Object Id="Desc_Task2" Chinese="切换英雄战斗教学" English="" French="" Spanish="" />
	<Object Id="Desc_Task3" Chinese="探索资源，制作大本营（火堆）" English="" French="" Spanish="" />
	<Object Id="Desc_Task4" Chinese="找一个合适的地方，使用火堆，扎营" English="" French="" Spanish="" />
	<Object Id="Desc_Task5" Chinese="首夜生存模式,建立新炮塔" English="" French="" Spanish="" />
	<Object Id="Desc_Task6" Chinese="PVP挑战对手" English="" French="" Spanish="" />
	<Object Id="Desc_Task7" Chinese="抽宝箱获取新英雄和宝石" English="" French="" Spanish="" />
	<Object Id="Desc_Task8" Chinese="宝石给英雄升星" English="" French="" Spanish="" />
	<Object Id="Desc_WarPack" Chinese="战争奖励礼包！" English="" French="" Spanish="" />
	<Object Id="LPID_ATK_FIRE" Chinese="火攻" English="Langage_14" French="" Spanish="" />
	<Object Id="LPID_ATK_ICE" Chinese="冰攻" English="Langage_17" French="" Spanish="" />
	<Object Id="LPID_ATK_LIGHT" Chinese="雷攻" English="Langage_15" French="" Spanish="" />
	<Object Id="LPID_ATK_POISON" Chinese="毒攻" English="Langage_18" French="" Spanish="" />
	<Object Id="LPID_ATK_SPEED" Chinese="攻击速度" English="Langage_13" French="" Spanish="" />
	<Object Id="LPID_ATK_VALUE" Chinese="物理攻击" English="Langage_10" French="" Spanish="" />
	<Object Id="LPID_ATK_WIND" Chinese="土攻" English="Langage_16" French="" Spanish="" />
	<Object Id="LPID_BUFF_GATE" Chinese="BUFF免疫开关" English="Langage_29" French="" Spanish="" />
	<Object Id="LPID_CRITICAL" Chinese="暴击" English="Langage_3" French="" Spanish="" />
	<Object Id="LPID_DEF_FIRE" Chinese="火防" English="Langage_19" French="" Spanish="" />
	<Object Id="LPID_DEF_ICE" Chinese="冰防" English="Langage_22" French="" Spanish="" />
	<Object Id="LPID_DEF_LIGHT" Chinese="雷防" English="Langage_20" French="" Spanish="" />
	<Object Id="LPID_DEF_POISON" Chinese="毒防" English="Langage_23" French="" Spanish="" />
	<Object Id="LPID_DEF_VALUE" Chinese="物理防御" English="Langage_11" French="" Spanish="" />
	<Object Id="LPID_DEF_WIND" Chinese="土防" English="Langage_21" French="" Spanish="" />
	<Object Id="LPID_DIZZY_GATE" Chinese="眩晕开关" English="Langage_24" French="" Spanish="" />
	<Object Id="LPID_HP" Chinese="生命" English="Langage_4" French="" Spanish="" />
	<Object Id="LPID_HPREGEN" Chinese="生命回复" English="Langage_7" French="" Spanish="" />
	<Object Id="LPID_MAGIC_GATE" Chinese="魔法免疫开关" English="sss" French="" Spanish="" />
	<Object Id="LPID_MAXHP" Chinese="生命上限" English="Langage_4" French="" Spanish="" />
	<Object Id="LPID_MAXMP" Chinese="法力上限" English="Langage_5" French="" Spanish="" />
	<Object Id="LPID_MAXSP" Chinese="体力上限" English="Langage_6" French="" Spanish="" />
	<Object Id="LPID_MOVE_GATE" Chinese="移动开关" English="Langage_25" French="" Spanish="" />
	<Object Id="LPID_MOVE_SPEED" Chinese="移动速度" English="Langage_12" French="" Spanish="" />
	<Object Id="LPID_MP" Chinese="法力" English="Langage_5" French="" Spanish="" />
	<Object Id="LPID_MPREGEN" Chinese="魔法回复" English="Langage_9" French="" Spanish="" />
	<Object Id="LPID_PHYSICAL_GATE" Chinese="物理免疫开关" English="Langage_27" French="" Spanish="" />
	<Object Id="LPID_REFLECTDAMAGE" Chinese="反伤" English="Langage_2" French="" Spanish="" />
	<Object Id="LPID_SKILL_GATE" Chinese="技能开关" English="Langage_26" French="" Spanish="" />
	<Object Id="LPID_SP" Chinese="体力" English="Langage_6" French="" Spanish="" />
	<Object Id="LPID_SPREGEN" Chinese="体力回复" English="Langage_8" French="" Spanish="" />
	<Object Id="LPID_SUCKBLOOD" Chinese="吸血" English="Langage_1" French="" Spanish="" />
	<Object Id="NameID_ATK_Water" Chinese="攻击药水" English="" French="" Spanish="" />
	<Object Id="NameID_Avoid_Def_Water" Chinese="防御药水" English="" French="" Spanish="" />
	<Object Id="NameID_Building000" Chinese="营地·一级" English="" French="" Spanish="" />
	<Object Id="NameID_Building001" Chinese="营地·二级" English="" French="" Spanish="" />
	<Object Id="NameID_Building002" Chinese="营地·三级" English="" French="" Spanish="" />
	<Object Id="NameID_Building010" Chinese="炸弹·一级" English="" French="" Spanish="" />
	<Object Id="NameID_Building011" Chinese="炸弹·二级" English="" French="" Spanish="" />
	<Object Id="NameID_Building012" Chinese="炸弹·三级" English="" French="" Spanish="" />
	<Object Id="NameID_Building020" Chinese="减甲炮·一级" English="" French="" Spanish="" />
	<Object Id="NameID_Building021" Chinese="减甲炮·二级" English="" French="" Spanish="" />
	<Object Id="NameID_Building022" Chinese="减甲炮·三级" English="" French="" Spanish="" />
	<Object Id="NameID_Building030" Chinese="加农炮·一级" English="" French="" Spanish="" />
	<Object Id="NameID_Building031" Chinese="加农炮·二级" English="" French="" Spanish="" />
	<Object Id="NameID_Building032" Chinese="加农炮·三级" English="" French="" Spanish="" />
	<Object Id="NameID_Building040" Chinese="冰塔·一级" English="" French="" Spanish="" />
	<Object Id="NameID_Building041" Chinese="冰塔·二级" English="" French="" Spanish="" />
	<Object Id="NameID_Building042" Chinese="冰塔·三级" English="" French="" Spanish="" />
	<Object Id="NameID_Building050" Chinese="能源产生器·一级" English="" French="" Spanish="" />
	<Object Id="NameID_Building051" Chinese="能源产生器·二级" English="" French="" Spanish="" />
	<Object Id="NameID_Building052" Chinese="能源产生器·三级" English="" French="" Spanish="" />
	<Object Id="NameID_Building060" Chinese="能源存储器·一级" English="" French="" Spanish="" />
	<Object Id="NameID_Building061" Chinese="能源存储器·二级" English="" French="" Spanish="" />
	<Object Id="NameID_Building062" Chinese="能源存储器·三级" English="" French="" Spanish="" />
	<Object Id="NameID_Building070" Chinese="火焰发射器·一级" English="" French="" Spanish="" />
	<Object Id="NameID_Building071" Chinese="火焰发射器·二级" English="" French="" Spanish="" />
	<Object Id="NameID_Building072" Chinese="火焰发射器·三级" English="" French="" Spanish="" />
	<Object Id="NameID_Building080" Chinese="加特林机枪·一级" English="" French="" Spanish="" />
	<Object Id="NameID_Building081" Chinese="加特林机枪·二级" English="" French="" Spanish="" />
	<Object Id="NameID_Building082" Chinese="加特林机枪·三级" English="" French="" Spanish="" />
	<Object Id="NameID_Building090" Chinese="高斯电磁炮·一级" English="" French="" Spanish="" />
	<Object Id="NameID_Building091" Chinese="高斯电磁炮·二级" English="" French="" Spanish="" />
	<Object Id="NameID_Building092" Chinese="高斯电磁炮·三级" English="" French="" Spanish="" />
	<Object Id="NameID_Building100" Chinese="金矿·一级" English="" French="" Spanish="" />
	<Object Id="NameID_Building101" Chinese="金矿·二级" English="" French="" Spanish="" />
	<Object Id="NameID_Building102" Chinese="金矿·三级" English="" French="" Spanish="" />
	<Object Id="NameID_Building110" Chinese="金罐·一级" English="" French="" Spanish="" />
	<Object Id="NameID_Building111" Chinese="金罐·二级" English="" French="" Spanish="" />
	<Object Id="NameID_Building112" Chinese="金罐·三级" English="" French="" Spanish="" />
	<Object Id="NameID_Building120" Chinese="重锤·一级" English="" French="" Spanish="" />
	<Object Id="NameID_Building121" Chinese="重锤·二级" English="" French="" Spanish="" />
	<Object Id="NameID_Building122" Chinese="重锤·三级" English="" French="" Spanish="" />
	<Object Id="NameID_Building130" Chinese="镭射激光器·一级" English="" French="" Spanish="" />
	<Object Id="NameID_Building131" Chinese="镭射激光器·二级" English="" French="" Spanish="" />
	<Object Id="NameID_Building132" Chinese="镭射激光器·三级" English="" French="" Spanish="" />
	<Object Id="NameID_Building140" Chinese="麦肯锡机枪·一级" English="" French="" Spanish="" />
	<Object Id="NameID_Building141" Chinese="麦肯锡机枪·二级" English="" French="" Spanish="" />
	<Object Id="NameID_Building142" Chinese="麦肯锡机枪·三级" English="" French="" Spanish="" />
	<Object Id="NameID_Building150" Chinese="迫击炮·一级" English="" French="" Spanish="" />
	<Object Id="NameID_Building151" Chinese="迫击炮·二级" English="" French="" Spanish="" />
	<Object Id="NameID_Building152" Chinese="迫击炮·三级" English="" French="" Spanish="" />
	<Object Id="NameID_Building160" Chinese="等离子炮·一级" English="" French="" Spanish="" />
	<Object Id="NameID_Building161" Chinese="等离子炮·二级" English="" French="" Spanish="" />
	<Object Id="NameID_Building162" Chinese="等离子炮·三级" English="" French="" Spanish="" />
	<Object Id="NameID_Building170" Chinese="探照灯·一级" English="" French="" Spanish="" />
	<Object Id="NameID_Building171" Chinese="探照灯·二级" English="" French="" Spanish="" />
	<Object Id="NameID_Building172" Chinese="探照灯·三级" English="" French="" Spanish="" />
	<Object Id="NameID_Building180" Chinese="雷达·一级" English="" French="" Spanish="" />
	<Object Id="NameID_Building181" Chinese="雷达·二级" English="" French="" Spanish="" />
	<Object Id="NameID_Building182" Chinese="雷达·三级" English="" French="" Spanish="" />
	<Object Id="NameID_Building190" Chinese="火箭·一级" English="" French="" Spanish="" />
	<Object Id="NameID_Building191" Chinese="火箭·二级" English="" French="" Spanish="" />
	<Object Id="NameID_Building192" Chinese="火箭·三级" English="" French="" Spanish="" />
	<Object Id="NameID_Building200" Chinese="雷电发射器·一级" English="" French="" Spanish="" />
	<Object Id="NameID_Building201" Chinese="雷电发射器·二级" English="" French="" Spanish="" />
	<Object Id="NameID_Building202" Chinese="雷电发射器·三级" English="" French="" Spanish="" />
	<Object Id="NameID_Building210" Chinese="穿刺怒·一级" English="" French="" Spanish="" />
	<Object Id="NameID_Building211" Chinese="穿刺怒·二级" English="" French="" Spanish="" />
	<Object Id="NameID_Building212" Chinese="穿刺怒·三级" English="" French="" Spanish="" />
	<Object Id="NameID_Building220" Chinese="火龙炮·一级" English="" French="" Spanish="" />
	<Object Id="NameID_Building221" Chinese="火龙炮·二级" English="" French="" Spanish="" />
	<Object Id="NameID_Building222" Chinese="火龙炮·三级" English="" French="" Spanish="" />
	<Object Id="NameID_Card_Hero001" Chinese="暗影刺客·英雄卷轴" English="" French="" Spanish="" />
	<Object Id="NameID_Card_Hero002" Chinese="唐僧·英雄卷轴" English="" French="" Spanish="" />
	<Object Id="NameID_Card_Hero003" Chinese="东洋忍者·英雄卷轴" English="" French="" Spanish="" />
	<Object Id="NameID_Card_Hero004" Chinese="溪涧武士·英雄卷轴" English="" French="" Spanish="" />
	<Object Id="NameID_Card_Hero005" Chinese="狂战士·英雄卷轴" English="" French="" Spanish="" />
	<Object Id="NameID_Card_Hero006" Chinese="库克船长·英雄卷轴" English="" French="" Spanish="" />
	<Object Id="NameID_Card_Hero007" Chinese="矮人国王·英雄卷轴" English="" French="" Spanish="" />
	<Object Id="NameID_Card_Hero008" Chinese="敌法师·英雄卷轴" English="" French="" Spanish="" />
	<Object Id="NameID_Card_Hero009" Chinese="花仙子·英雄卷轴" English="" French="" Spanish="" />
	<Object Id="NameID_Card_Hero010" Chinese="马尔斯·英雄卷轴" English="" French="" Spanish="" />
	<Object Id="NameID_Card_Hero011" Chinese="艾里斯·英雄卷轴" English="" French="" Spanish="" />
	<Object Id="NameID_Card_Hero012" Chinese="地狱火·英雄卷轴" English="" French="" Spanish="" />
	<Object Id="NameID_Card_Hero013" Chinese="骷髅射手·英雄卷轴" English="" French="" Spanish="" />
	<Object Id="NameID_Card_Hero014" Chinese="暗影萨满·英雄卷轴" English="" French="" Spanish="" />
	<Object Id="NameID_Card_Hero015" Chinese="鼠人·英雄卷轴" English="" French="" Spanish="" />
	<Object Id="NameID_Card_Hero016" Chinese="矮人·英雄卷轴" English="" French="" Spanish="" />
	<Object Id="NameID_Card_Hero017" Chinese="食人魔·英雄卷轴" English="" French="" Spanish="" />
	<Object Id="NameID_Card_Hero018" Chinese="孙悟空·英雄卷轴" English="" French="" Spanish="" />
	<Object Id="NameID_Card_Hero019" Chinese="圆桌骑士·英雄卷轴" English="" French="" Spanish="" />
	<Object Id="NameID_Damage_MP_Water" Chinese="消魔药水" English="" French="" Spanish="" />
	<Object Id="NameID_Diamond_Item1" Chinese="钻石" English="" French="" Spanish="" />
	<Object Id="NameID_GEM_ATK" Chinese="攻击宝石" English="" French="" Spanish="" />
	<Object Id="NameID_GEM_DEF" Chinese="防御宝石" English="" French="" Spanish="" />
	<Object Id="NameID_GEM_FIRE" Chinese="火属性宝石" English="" French="" Spanish="" />
	<Object Id="NameID_GEM_ICE" Chinese="冰属性宝石" English="" French="" Spanish="" />
	<Object Id="NameID_GEM_LIGHT" Chinese="雷属性宝石" English="" French="" Spanish="" />
	<Object Id="NameID_GEM_POISON" Chinese="毒属性宝石" English="" French="" Spanish="" />
	<Object Id="NameID_GEM_WIND" Chinese="风属性宝石" English="" French="" Spanish="" />
	<Object Id="NameID_Gold_Item1" Chinese="金币" English="" French="" Spanish="" />
	<Object Id="NameID_HOLY_WATER" Chinese="圣水" English="" French="" Spanish="" />
	<Object Id="NameID_HP" Chinese="血药" English="" French="" Spanish="" />
	<Object Id="NameID_Hero001" Chinese="暗影刺客" English="Orcs · Slinger" French="" Spanish="" />
	<Object Id="NameID_Hero002" Chinese="唐僧" English="Dwarf · Gold Digger" French="" Spanish="" />
	<Object Id="NameID_Hero003" Chinese="东洋忍者" English="Orcs · Wererat" French="" Spanish="" />
	<Object Id="NameID_Hero004" Chinese="溪涧武士" English="Human · Yao Li" French="" Spanish="" />
	<Object Id="NameID_Hero005" Chinese="狂战士" English="" French="" Spanish="" />
	<Object Id="NameID_Hero006" Chinese="库克船长" English="" French="" Spanish="" />
	<Object Id="NameID_Hero007" Chinese="矮人国王" English="" French="" Spanish="" />
	<Object Id="NameID_Hero008" Chinese="敌法师" English="" French="" Spanish="" />
	<Object Id="NameID_Hero009" Chinese="花仙子" English="" French="" Spanish="" />
	<Object Id="NameID_Hero010" Chinese="斯巴达克斯" English="Spartacus" French="" Spanish="" />
	<Object Id="NameID_Hero011" Chinese="火狱领主" English="Fire of Lord" French="" Spanish="" />
	<Object Id="NameID_Hero012" Chinese="地狱火" English="" French="" Spanish="" />
	<Object Id="NameID_Hero013" Chinese="骷髅射手" English="" French="" Spanish="" />
	<Object Id="NameID_Hero014" Chinese="暗影萨满" English="" French="" Spanish="" />
	<Object Id="NameID_Hero015" Chinese="鼠人" English="" French="" Spanish="" />
	<Object Id="NameID_Hero016" Chinese="矮人" English="" French="" Spanish="" />
	<Object Id="NameID_Hero017" Chinese="食人魔" English="" French="" Spanish="" />
	<Object Id="NameID_Hero018" Chinese="孙悟空" English="" French="" Spanish="" />
	<Object Id="NameID_Hero019" Chinese="圆桌骑士" English="" French="" Spanish="" />
	<Object Id="NameID_MP" Chinese="蓝药" English="" French="" Spanish="" />
	<Object Id="NameID_NPC001" Chinese="兽族 · 食人魔" English="Orcs · Slinger" French="" Spanish="" />
	<Object Id="NameID_NPC002" Chinese="矮人 · 掘金者" English="Dwarf · Gold Digger" French="" Spanish="" />
	<Object Id="NameID_NPC003" Chinese="兽族 · 狼人" English="Orcs · Wererat" French="" Spanish="" />
	<Object Id="NameID_NPC004" Chinese="人族 · 要离" English="Human · Yao Li" French="" Spanish="" />
	<Object Id="NameID_NPC005" Chinese="" English="" French="" Spanish="" />
	<Object Id="NameID_NPC006" Chinese="" English="" French="" Spanish="" />
	<Object Id="NameID_NPC007" Chinese="" English="" French="" Spanish="" />
	<Object Id="NameID_NPC008" Chinese="" English="" French="" Spanish="" />
	<Object Id="NameID_NPC009" Chinese="" English="" French="" Spanish="" />
	<Object Id="NameID_NPC010" Chinese="" English="" French="" Spanish="" />
	<Object Id="NameID_NPC011" Chinese="" English="" French="" Spanish="" />
	<Object Id="NameID_NPC012" Chinese="" English="" French="" Spanish="" />
	<Object Id="NameID_NPC013" Chinese="" English="" French="" Spanish="" />
	<Object Id="NameID_NPC014" Chinese="" English="" French="" Spanish="" />
	<Object Id="NameID_NPC015" Chinese="" English="" French="" Spanish="" />
	<Object Id="NameID_NPC016" Chinese="" English="" French="" Spanish="" />
	<Object Id="NameID_NPC017" Chinese="" English="" French="" Spanish="" />
	<Object Id="NameID_NPC018" Chinese="" English="" French="" Spanish="" />
	<Object Id="NameID_NPC019" Chinese="" English="" French="" Spanish="" />
	<Object Id="NameID_NoobPack" Chinese="新手礼包" English="" French="" Spanish="" />
	<Object Id="NameID_Special1_Hero001" Chinese="技能1*英雄1" English="" French="" Spanish="" />
	<Object Id="NameID_Special1_Hero002" Chinese="技能1*英雄2" English="" French="" Spanish="" />
	<Object Id="NameID_Special1_Hero003" Chinese="技能1*英雄3" English="" French="" Spanish="" />
	<Object Id="NameID_Special1_Hero004" Chinese="技能1*英雄4" English="" French="" Spanish="" />
	<Object Id="NameID_Special1_Hero005" Chinese="技能1*英雄5" English="" French="" Spanish="" />
	<Object Id="NameID_Special1_Hero006" Chinese="技能1*英雄6" English="" French="" Spanish="" />
	<Object Id="NameID_Special1_Hero007" Chinese="技能1*英雄7" English="" French="" Spanish="" />
	<Object Id="NameID_Special1_Hero008" Chinese="技能1*英雄8" English="" French="" Spanish="" />
	<Object Id="NameID_Special1_Hero009" Chinese="技能1*英雄9" English="" French="" Spanish="" />
	<Object Id="NameID_Special1_Hero010" Chinese="技能1*英雄10" English="" French="" Spanish="" />
	<Object Id="NameID_Special1_Hero011" Chinese="技能1*英雄11" English="" French="" Spanish="" />
	<Object Id="NameID_Special1_Hero012" Chinese="技能1*英雄12" English="" French="" Spanish="" />
	<Object Id="NameID_Special1_Hero013" Chinese="技能1*英雄13" English="" French="" Spanish="" />
	<Object Id="NameID_Special1_Hero014" Chinese="技能1*英雄14" English="" French="" Spanish="" />
	<Object Id="NameID_Special1_Hero015" Chinese="技能1*英雄15" English="" French="" Spanish="" />
	<Object Id="NameID_Special1_Hero016" Chinese="技能1*英雄16" English="" French="" Spanish="" />
	<Object Id="NameID_Special1_Hero017" Chinese="技能1*英雄17" English="" French="" Spanish="" />
	<Object Id="NameID_Special1_Hero018" Chinese="技能1*英雄18" English="" French="" Spanish="" />
	<Object Id="NameID_Special1_Hero019" Chinese="技能1*英雄19" English="" French="" Spanish="" />
	<Object Id="NameID_Special2_Hero001" Chinese="技能2*英雄1" English="" French="" Spanish="" />
	<Object Id="NameID_Special2_Hero002" Chinese="技能2*英雄2" English="" French="" Spanish="" />
	<Object Id="NameID_Special2_Hero003" Chinese="技能2*英雄3" English="" French="" Spanish="" />
	<Object Id="NameID_Special2_Hero004" Chinese="技能2*英雄4" English="" French="" Spanish="" />
	<Object Id="NameID_Special2_Hero005" Chinese="技能2*英雄5" English="" French="" Spanish="" />
	<Object Id="NameID_Special2_Hero006" Chinese="技能2*英雄6" English="" French="" Spanish="" />
	<Object Id="NameID_Special2_Hero007" Chinese="技能2*英雄7" English="" French="" Spanish="" />
	<Object Id="NameID_Special2_Hero008" Chinese="技能2*英雄8" English="" French="" Spanish="" />
	<Object Id="NameID_Special2_Hero009" Chinese="技能2*英雄9" English="" French="" Spanish="" />
	<Object Id="NameID_Special2_Hero010" Chinese="技能2*英雄10" English="" French="" Spanish="" />
	<Object Id="NameID_Special2_Hero011" Chinese="技能2*英雄11" English="" French="" Spanish="" />
	<Object Id="NameID_Special2_Hero012" Chinese="技能2*英雄12" English="" French="" Spanish="" />
	<Object Id="NameID_Special2_Hero013" Chinese="技能2*英雄13" English="" French="" Spanish="" />
	<Object Id="NameID_Special2_Hero014" Chinese="技能2*英雄14" English="" French="" Spanish="" />
	<Object Id="NameID_Special2_Hero015" Chinese="技能2*英雄15" English="" French="" Spanish="" />
	<Object Id="NameID_Special2_Hero016" Chinese="技能2*英雄16" English="" French="" Spanish="" />
	<Object Id="NameID_Special2_Hero017" Chinese="技能2*英雄17" English="" French="" Spanish="" />
	<Object Id="NameID_Special2_Hero018" Chinese="技能2*英雄18" English="" French="" Spanish="" />
	<Object Id="NameID_Special2_Hero019" Chinese="技能2*英雄19" English="" French="" Spanish="" />
	<Object Id="NameID_THUMP_Hero001" Chinese="觉醒技能*英雄001" English="" French="" Spanish="" />
	<Object Id="NameID_THUMP_Hero002" Chinese="觉醒技能*英雄002" English="" French="" Spanish="" />
	<Object Id="NameID_THUMP_Hero003" Chinese="觉醒技能*英雄003" English="" French="" Spanish="" />
	<Object Id="NameID_THUMP_Hero004" Chinese="觉醒技能*英雄004" English="" French="" Spanish="" />
	<Object Id="NameID_THUMP_Hero005" Chinese="觉醒技能*英雄005" English="" French="" Spanish="" />
	<Object Id="NameID_THUMP_Hero006" Chinese="觉醒技能*英雄006" English="" French="" Spanish="" />
	<Object Id="NameID_THUMP_Hero007" Chinese="觉醒技能*英雄007" English="" French="" Spanish="" />
	<Object Id="NameID_THUMP_Hero008" Chinese="觉醒技能*英雄008" English="" French="" Spanish="" />
	<Object Id="NameID_THUMP_Hero009" Chinese="觉醒技能*英雄009" English="" French="" Spanish="" />
	<Object Id="NameID_THUMP_Hero010" Chinese="觉醒技能*英雄010" English="" French="" Spanish="" />
	<Object Id="NameID_THUMP_Hero011" Chinese="觉醒技能*英雄011" English="" French="" Spanish="" />
	<Object Id="NameID_THUMP_Hero012" Chinese="觉醒技能*英雄012" English="" French="" Spanish="" />
	<Object Id="NameID_THUMP_Hero013" Chinese="觉醒技能*英雄013" English="" French="" Spanish="" />
	<Object Id="NameID_THUMP_Hero014" Chinese="觉醒技能*英雄014" English="" French="" Spanish="" />
	<Object Id="NameID_THUMP_Hero015" Chinese="觉醒技能*英雄015" English="" French="" Spanish="" />
	<Object Id="NameID_THUMP_Hero016" Chinese="觉醒技能*英雄016" English="" French="" Spanish="" />
	<Object Id="NameID_THUMP_Hero017" Chinese="觉醒技能*英雄017" English="" French="" Spanish="" />
	<Object Id="NameID_THUMP_Hero018" Chinese="觉醒技能*英雄018" English="" French="" Spanish="" />
	<Object Id="NameID_THUMP_Hero019" Chinese="觉醒技能*英雄019" English="" French="" Spanish="" />
	<Object Id="NameID_WarPack" Chinese="战争礼包" English="" French="" Spanish="" />
	<Object Id="ui_OK" Chinese="确认" English="OK" French="" Spanish="" />
	<Object Id="ui_cancel" Chinese="取消" English="CANCEL" French="" Spanish="" />
	<Object Id="ui_cn" Chinese="中文" English="Chinese" French="" Spanish="" />
	<Object Id="ui_enter" Chinese="进入游戏" English="Enter" French="" Spanish="" />
	<Object Id="ui_login" Chinese="登录" English="Login" French="" Spanish="" />
</XML>